ShynaFaceRecognition/__init__.py
ShynaFaceRecognition/face.py
ShynaFaceRecognition-0.25.dist-info/LICENSE
ShynaFaceRecognition-0.25.dist-info/METADATA
ShynaFaceRecognition-0.25.dist-info/WHEEL
ShynaFaceRecognition-0.25.dist-info/top_level.txt
ShynaFaceRecognition-0.25.dist-info/RECORD
