Metadata-Version: 2.1
Name: ShynaFaceRecognition
Version: 0.25
Summary: This package will take care of face recognition.
Author: Shivam Sharma
Author-email: shivamsharma1913@gmail.com
License-File: LICENSE
Requires-Dist: ShynaDatabase
Requires-Dist: ShynaTime
Requires-Dist: face-recognition
Requires-Dist: setuptools
Requires-Dist: wheel
